{
  "name": "CommunityInstitutes",
  "options": {
    "idInjection": false,
    "mysql": {
      "schema": "plan_it",
      "table": "COMMUNITY_INSTITUTES"
    }
  },
  "properties": {
    "ciId": {
      "type": "Number",
      "required": true,
      "length": null,
      "precision": 10,
      "scale": 0,
      "id": 1,
      "mysql": {
        "columnName": "CI_ID",
        "dataType": "int",
        "dataLength": null,
        "dataPrecision": 10,
        "dataScale": 0,
        "nullable": "N"
      }
    },
    "ciName": {
      "type": "String",
      "required": false,
      "length": 65535,
      "precision": null,
      "scale": null,
      "mysql": {
        "columnName": "CI_NAME",
        "dataType": "text",
        "dataLength": 65535,
        "dataPrecision": null,
        "dataScale": null,
        "nullable": "Y"
      }
    },
    "ciType": {
      "type": "String",
      "required": false,
      "length": 65535,
      "precision": null,
      "scale": null,
      "mysql": {
        "columnName": "CI_TYPE",
        "dataType": "text",
        "dataLength": 65535,
        "dataPrecision": null,
        "dataScale": null,
        "nullable": "Y"
      }
    },
    "ciPurpose": {
      "type": "String",
      "required": false,
      "length": 65535,
      "precision": null,
      "scale": null,
      "mysql": {
        "columnName": "CI_PURPOSE",
        "dataType": "text",
        "dataLength": 65535,
        "dataPrecision": null,
        "dataScale": null,
        "nullable": "Y"
      }
    },
    "ciMember": {
      "type": "Number",
      "required": false,
      "length": null,
      "precision": 10,
      "scale": 0,
      "mysql": {
        "columnName": "CI_MEMBER",
        "dataType": "int",
        "dataLength": null,
        "dataPrecision": 10,
        "dataScale": 0,
        "nullable": "Y"
      }
    },
    "viId": {
      "type": "Number",
      "required": true,
      "length": null,
      "precision": 10,
      "scale": 0,
      "mysql": {
        "columnName": "VI_ID",
        "dataType": "int",
        "dataLength": null,
        "dataPrecision": 10,
        "dataScale": 0,
        "nullable": "N"
      }
    }
  }
}