{
  "name": "InstituteVillageRel",
  "options": {
    "idInjection": false,
    "mysql": {
      "schema": "plan_it",
      "table": "INSTITUTE_VILLAGE_REL"
    }
  },
  "properties": {
    "instViId": {
      "type": "Number",
      "required": true,
      "length": null,
      "precision": 10,
      "scale": 0,
      "id": 1,
      "mysql": {
        "columnName": "INST_VI_ID",
        "dataType": "int",
        "dataLength": null,
        "dataPrecision": 10,
        "dataScale": 0,
        "nullable": "N"
      }
    },
    "instId": {
      "type": "Number",
      "required": true,
      "length": null,
      "precision": 10,
      "scale": 0,
      "mysql": {
        "columnName": "INST_ID",
        "dataType": "int",
        "dataLength": null,
        "dataPrecision": 10,
        "dataScale": 0,
        "nullable": "N"
      }
    },
    "viId": {
      "type": "Number",
      "required": true,
      "length": null,
      "precision": 10,
      "scale": 0,
      "mysql": {
        "columnName": "VI_ID",
        "dataType": "int",
        "dataLength": null,
        "dataPrecision": 10,
        "dataScale": 0,
        "nullable": "N"
      }
    }
  }
}